Workbook

Sheet README
A1: Lab 3b: Cybersecurity Risk Quantification - SecureBank Financial / SecureMobile
A4: Purpose | B4: Quantifies financial risk of three critical findings, evaluates three controls, and supports the executive briefing.
A5: How to use | B5: Change numbers only on the Inputs tab (blue text). Every other tab recalculates from it.
A6: Colour code | B6: Blue = input from the lab dataset or analyst assumption | Black = formula | Green = link to another sheet.
A8: Tab | B8: What it covers
A9: Inputs | B9: Dataset from the lab sheet, plus thresholds, budget and horizon assumptions.
A10: Risk Calc | B10: Tasks 1-2: SLE, ARO, ALE, risk priority matrix, residual ALE, and the risk heat map grid (Task 3).
A11: Control Analysis | B11: Task 4: initial cost, maintenance, risk reduction, ROI, payback for each control.
A12: Charts | B12: Tasks 3 and 5: ALE bar, risk distribution pie, cost vs effectiveness scatter, ROI bar, risk reduction line.
A13: Dashboard | B13: Task 6: one-page executive dashboard with the three required charts.
A14: Gantt | B14: Task 7: risk treatment timeline (30 days / 90 days / 1 year).
A15: Bonus | B15: Optimal control selection under a budget and combined risk-control matrix.
A16: Chart Data | B16: Helper ranges that feed the charts. No inputs here.
A18: Key assumptions
A19: 1 | B19: SLE for Finding 1 = stated maximum single-incident loss ($5M). Finding 2 SLE = records x cost per record. Finding 3 SLE = accounts at risk x average loss per account.
A20: 2 | B20: ARO = stated exploit probability (one expected exploitation attempt per year at that likelihood).
A21: 3 | B21: Each control is applied only to the finding it addresses (mapping on Inputs, column F). Effectiveness % is taken as given.
A22: 4 | B22: Risk reduction = ALE x effectiveness. Year-1 cost = initial cost + one year of maintenance. ROI = (benefit - cost) / cost.
A23: 5 | B23: Payback (months) = initial cost / (annual risk reduction - annual maintenance) x 12.
A24: 6 | B24: Risk-level thresholds on Inputs (rows 24-30) are analyst assumptions, not given in the lab. Change them and priorities update.
A25: 7 | B25: Limitation: Finding 1 has a 48-hour detection window. At the stated volumes the real loss could exceed the $5M cap, so Finding 1 may be understated.
A26: 8 | B26: Limitation: the WAF is credited with 75% of the injection ALE, so its ROI is very large. The vulnerability should still be fixed in code; a WAF is a compensating control.

Sheet Inputs
A1: Inputs - Lab 3b dataset and assumptions
A2: Blue cells are inputs. Source: Lab 3b dataset unless marked 'assumption'.
A4: System context
A5: Platform | B5: SecureMobile
A6: Active customers | B6: 500000
A7: Average transaction ($) | B7: 2500
A8: Daily transactions | B8: 50000
A11: Vulnerability findings
A12: # | B12: Finding | C12: Exploit probability | D12: Max single incident loss ($) | E12: Records at risk | F12: Cost per record ($) | G12: Accounts at risk | H12: Avg loss per account ($) | I12: Systems affected | J12: Potential impact | K12: Est. detection (hrs)
A13: 1 | B13: API Authentication Bypass | C13: 0.15 | D13: 5000000 | I13: Transaction processing system | J13: Unauthorized fund transfers | K13: 48
A14: 2 | B14: Database Injection | C14: 0.25 | E14: 500000 | F14: 250 | I14: Customer database | J14: Data breach (PII + financial data)
A15: 3 | B15: Session Hijacking | C15: 0.4 | G15: 5000 | H15: 1500 | I15: User sessions | J15: Account takeover
A17: Control options
A18: # | B18: Control | C18: Initial cost ($) | D18: Effectiveness | E18: Annual maintenance ($) | F18: Addresses finding # | G18: Mapping rationale (assumption)
A19: 1 | B19: Advanced API Security Gateway | C19: 350000 | D19: 0.9 | E19: 50000 | F19: 1 | G19: Targets API vulnerabilities (Finding 1)
A20: 2 | B20: Web Application Firewall (WAF) | C20: 150000 | D20: 0.75 | E20: 25000 | F20: 2 | G20: Blocks web-layer injection attacks (Finding 2)
A21: 3 | B21: Multi-Factor Authentication Enhancement | C21: 200000 | D21: 0.95 | E21: 30000 | F21: 3 | G21: Reduces account takeover (Finding 3)
A23: Analysis parameters (analyst assumptions)
A24: Critical priority: ALE at or above ($) | B24: 10000000 | C24: Assumption
A25: High priority: ALE at or above ($) | B25: 1000000 | C25: Assumption
A26: Medium priority: ALE at or above ($) | B26: 500000 | C26: Assumption; below this = Low
A27: Probability 'High' at or above | B27: 0.3 | C27: Assumption for heat map
A28: Probability 'Medium' at or above | B28: 0.15 | C28: Assumption for heat map; below = Low
A29: Impact 'High' (SLE) at or above ($) | B29: 50000000 | C29: Assumption for heat map
A30: Impact 'Medium' (SLE) at or above ($) | B30: 5000000 | C30: Assumption for heat map; below = Low
A31: Analysis horizon (years) | B31: 3 | C31: Assumption for multi-year ROI
A32: Minimum Year-1 ROI to recommend a control | B32: 0.5 | C32: Assumption (hurdle rate)
A33: Year-1 security budget for Bonus ($) | B33: 500000 | C33: Assumption; not given in lab. Edit to test scenarios

Sheet Risk Calc
A1: Phase 1 - Risk exposure (Tasks 1-2) and heat map (Task 3)
A2: ALE = SLE x ARO. Thresholds are set on Inputs rows 24-30.
A4: # | B4: Vulnerability | C4: SLE ($) | D4: ARO | E4: ALE ($) | F4: % of total ALE | G4: Rank | H4: Risk priority | I4: Probability level | J4: Impact level | K4: Heat rating | L4: Residual ALE after controls ($) | M4: SLE basis
A5: =Inputs!A13 -> 1 | B5: =Inputs!B13 -> API Authentication Bypass | C5: =Inputs!D13 -> 5000000 | D5: =Inputs!C13 -> 0.15 | E5: =C5*D5 -> 750000 | F5: =E5/$E$8 -> 0.021428571 | G5: =RANK(E5,$E$5:$E$7,0) -> 3 | H5: =IF(E5>=Inputs!$B$24,"Critical",IF(E5>=Inputs!$B$25,"High",IF(E5>=Inputs!$B$26,"Medium","Low"))) -> Medium | I5: =IF(D5>=Inputs!$B$27,"High",IF(D5>=Inputs!$B$28,"Medium","Low")) -> Medium | J5: =IF(C5>=Inputs!$B$29,"High",IF(C5>=Inputs!$B$30,"Medium","Low")) -> Medium | K5: =IF(((I5="High")*3+(I5="Medium")*2+(I5="Low")*1+(J5="High")*3+(J5="Medium")*2+(J5="Low")*1)>=5,"High",IF(((I5="High")*3+(I5="Medium")*2+(I5="Low")*1+(J5="High")*3+(J5="Medium")*2+(J5="Low")*1)=4,"Medium","Low")) -> Medium | L5: =E5-SUMIFS('Control Analysis'!$G$5:$G$7,'Control Analysis'!$C$5:$C$7,A5) -> 75000 | M5: Stated maximum single-incident loss
A6: =Inputs!A14 -> 2 | B6: =Inputs!B14 -> Database Injection | C6: =Inputs!E14*Inputs!F14 -> 125000000 | D6: =Inputs!C14 -> 0.25 | E6: =C6*D6 -> 31250000 | F6: =E6/$E$8 -> 0.89285714 | G6: =RANK(E6,$E$5:$E$7,0) -> 1 | H6: =IF(E6>=Inputs!$B$24,"Critical",IF(E6>=Inputs!$B$25,"High",IF(E6>=Inputs!$B$26,"Medium","Low"))) -> Critical | I6: =IF(D6>=Inputs!$B$27,"High",IF(D6>=Inputs!$B$28,"Medium","Low")) -> Medium | J6: =IF(C6>=Inputs!$B$29,"High",IF(C6>=Inputs!$B$30,"Medium","Low")) -> High | K6: =IF(((I6="High")*3+(I6="Medium")*2+(I6="Low")*1+(J6="High")*3+(J6="Medium")*2+(J6="Low")*1)>=5,"High",IF(((I6="High")*3+(I6="Medium")*2+(I6="Low")*1+(J6="High")*3+(J6="Medium")*2+(J6="Low")*1)=4,"Medium","Low")) -> High | L6: =E6-SUMIFS('Control Analysis'!$G$5:$G$7,'Control Analysis'!$C$5:$C$7,A6) -> 7812500 | M6: 500,000 records x $250 per record
A7: =Inputs!A15 -> 3 | B7: =Inputs!B15 -> Session Hijacking | C7: =Inputs!G15*Inputs!H15 -> 7500000 | D7: =Inputs!C15 -> 0.4 | E7: =C7*D7 -> 3000000 | F7: =E7/$E$8 -> 0.085714286 | G7: =RANK(E7,$E$5:$E$7,0) -> 2 | H7: =IF(E7>=Inputs!$B$24,"Critical",IF(E7>=Inputs!$B$25,"High",IF(E7>=Inputs!$B$26,"Medium","Low"))) -> High | I7: =IF(D7>=Inputs!$B$27,"High",IF(D7>=Inputs!$B$28,"Medium","Low")) -> High | J7: =IF(C7>=Inputs!$B$29,"High",IF(C7>=Inputs!$B$30,"Medium","Low")) -> Medium | K7: =IF(((I7="High")*3+(I7="Medium")*2+(I7="Low")*1+(J7="High")*3+(J7="Medium")*2+(J7="Low")*1)>=5,"High",IF(((I7="High")*3+(I7="Medium")*2+(I7="Low")*1+(J7="High")*3+(J7="Medium")*2+(J7="Low")*1)=4,"Medium","Low")) -> High | L7: =E7-SUMIFS('Control Analysis'!$G$5:$G$7,'Control Analysis'!$C$5:$C$7,A7) -> 150000 | M7: 5,000 accounts x $1,500 per account
B8: Total | C8: =SUM(C5:C7) -> 137500000 | E8: =SUM(E5:E7) -> 35000000 | F8: =SUM(F5:F7) -> 1 | L8: =SUM(L5:L7) -> 8037500 | M8: Total SLE is a sum of independent worst cases, shown for reference only
A11: Risk heat map: probability (rows) x impact / SLE (columns). F1-F3 = finding numbers.
A12: Probability \ Impact | B12: Low | C12: Medium | D12: High
A13: High | B13: =TRIM(IF(AND($I$5=$A13,$J$5=B$12),"F"&$A$5&" ","")&IF(AND($I$6=$A13,$J$6=B$12),"F"&$A$6&" ","")&IF(AND($I$7=$A13,$J$7=B$12),"F"&$A$7&" ","")) | C13: =TRIM(IF(AND($I$5=$A13,$J$5=C$12),"F"&$A$5&" ","")&IF(AND($I$6=$A13,$J$6=C$12),"F"&$A$6&" ","")&IF(AND($I$7=$A13,$J$7=C$12),"F"&$A$7&" ","")) -> F3 | D13: =TRIM(IF(AND($I$5=$A13,$J$5=D$12),"F"&$A$5&" ","")&IF(AND($I$6=$A13,$J$6=D$12),"F"&$A$6&" ","")&IF(AND($I$7=$A13,$J$7=D$12),"F"&$A$7&" ",""))
A14: Medium | B14: =TRIM(IF(AND($I$5=$A14,$J$5=B$12),"F"&$A$5&" ","")&IF(AND($I$6=$A14,$J$6=B$12),"F"&$A$6&" ","")&IF(AND($I$7=$A14,$J$7=B$12),"F"&$A$7&" ","")) | C14: =TRIM(IF(AND($I$5=$A14,$J$5=C$12),"F"&$A$5&" ","")&IF(AND($I$6=$A14,$J$6=C$12),"F"&$A$6&" ","")&IF(AND($I$7=$A14,$J$7=C$12),"F"&$A$7&" ","")) -> F1 | D14: =TRIM(IF(AND($I$5=$A14,$J$5=D$12),"F"&$A$5&" ","")&IF(AND($I$6=$A14,$J$6=D$12),"F"&$A$6&" ","")&IF(AND($I$7=$A14,$J$7=D$12),"F"&$A$7&" ","")) -> F2
A15: Low | B15: =TRIM(IF(AND($I$5=$A15,$J$5=B$12),"F"&$A$5&" ","")&IF(AND($I$6=$A15,$J$6=B$12),"F"&$A$6&" ","")&IF(AND($I$7=$A15,$J$7=B$12),"F"&$A$7&" ","")) | C15: =TRIM(IF(AND($I$5=$A15,$J$5=C$12),"F"&$A$5&" ","")&IF(AND($I$6=$A15,$J$6=C$12),"F"&$A$6&" ","")&IF(AND($I$7=$A15,$J$7=C$12),"F"&$A$7&" ","")) | D15: =TRIM(IF(AND($I$5=$A15,$J$5=D$12),"F"&$A$5&" ","")&IF(AND($I$6=$A15,$J$6=D$12),"F"&$A$6&" ","")&IF(AND($I$7=$A15,$J$7=D$12),"F"&$A$7&" ",""))
A17: Key: | B17: High risk | C17: Medium risk | D17: Low risk

Sheet Control Analysis
A1: Phase 2 - Control cost-benefit analysis (Task 4)
A2: Risk reduction = ALE of addressed finding x effectiveness. ROI = (benefit - cost) / cost.
A4: # | B4: Control | C4: Finding # | D4: Finding addressed | E4: Target ALE ($) | F4: Effectiveness | G4: Annual risk reduction ($) | H4: Initial investment ($) | I4: Annual maintenance ($) | J4: Year-1 cost ($) | K4: Year-1 ROI | L4: Payback (months) | M4: Payback (days) | N4: Multi-year cost ($) | O4: Multi-year benefit ($) | P4: Multi-year ROI | Q4: Net annual benefit ($) | R4: Recommendation
A5: =Inputs!A19 -> 1 | B5: =Inputs!B19 -> Advanced API Security Gateway | C5: =Inputs!F19 -> 1 | D5: =INDEX(Inputs!$B$13:$B$15,MATCH(C5,Inputs!$A$13:$A$15,0)) -> API Authentication Bypass | E5: =INDEX('Risk Calc'!$E$5:$E$7,MATCH(C5,'Risk Calc'!$A$5:$A$7,0)) -> 750000 | F5: =Inputs!D19 -> 0.9 | G5: =E5*F5 -> 675000 | H5: =Inputs!C19 -> 350000 | I5: =Inputs!E19 -> 50000 | J5: =H5+I5 -> 400000 | K5: =IF(J5=0,0,(G5-J5)/J5) -> 0.6875 | L5: =IF(G5-I5<=0,"n/a",H5/(G5-I5)*12) -> 6.72 | M5: =IF(ISNUMBER(L5),L5*30.4375,"n/a") -> 204.54 | N5: =H5+I5*Inputs!$B$31 -> 500000 | O5: =G5*Inputs!$B$31 -> 2025000 | P5: =IF(N5=0,0,(O5-N5)/N5) -> 3.05 | Q5: =G5-I5 -> 625000 | R5: =IF(K5>=Inputs!$B$32,"Recommend","Review") -> Recommend
A6: =Inputs!A20 -> 2 | B6: =Inputs!B20 -> Web Application Firewall (WAF) | C6: =Inputs!F20 -> 2 | D6: =INDEX(Inputs!$B$13:$B$15,MATCH(C6,Inputs!$A$13:$A$15,0)) -> Database Injection | E6: =INDEX('Risk Calc'!$E$5:$E$7,MATCH(C6,'Risk Calc'!$A$5:$A$7,0)) -> 31250000 | F6: =Inputs!D20 -> 0.75 | G6: =E6*F6 -> 23437500 | H6: =Inputs!C20 -> 150000 | I6: =Inputs!E20 -> 25000 | J6: =H6+I6 -> 175000 | K6: =IF(J6=0,0,(G6-J6)/J6) -> 132.92857 | L6: =IF(G6-I6<=0,"n/a",H6/(G6-I6)*12) -> 0.076882007 | M6: =IF(ISNUMBER(L6),L6*30.4375,"n/a") -> 2.3400961 | N6: =H6+I6*Inputs!$B$31 -> 225000 | O6: =G6*Inputs!$B$31 -> 70312500 | P6: =IF(N6=0,0,(O6-N6)/N6) -> 311.5 | Q6: =G6-I6 -> 23412500 | R6: =IF(K6>=Inputs!$B$32,"Recommend","Review") -> Recommend
A7: =Inputs!A21 -> 3 | B7: =Inputs!B21 -> Multi-Factor Authentication Enhancement | C7: =Inputs!F21 -> 3 | D7: =INDEX(Inputs!$B$13:$B$15,MATCH(C7,Inputs!$A$13:$A$15,0)) -> Session Hijacking | E7: =INDEX('Risk Calc'!$E$5:$E$7,MATCH(C7,'Risk Calc'!$A$5:$A$7,0)) -> 3000000 | F7: =Inputs!D21 -> 0.95 | G7: =E7*F7 -> 2850000 | H7: =Inputs!C21 -> 200000 | I7: =Inputs!E21 -> 30000 | J7: =H7+I7 -> 230000 | K7: =IF(J7=0,0,(G7-J7)/J7) -> 11.391304 | L7: =IF(G7-I7<=0,"n/a",H7/(G7-I7)*12) -> 0.85106383 | M7: =IF(ISNUMBER(L7),L7*30.4375,"n/a") -> 25.904255 | N7: =H7+I7*Inputs!$B$31 -> 290000 | O7: =G7*Inputs!$B$31 -> 8550000 | P7: =IF(N7=0,0,(O7-N7)/N7) -> 28.482759 | Q7: =G7-I7 -> 2820000 | R7: =IF(K7>=Inputs!$B$32,"Recommend","Review") -> Recommend
B8: Total (all three controls) | G8: =SUM(G5:G7) -> 26962500 | H8: =SUM(H5:H7) -> 700000 | I8: =SUM(I5:I7) -> 105000 | J8: =SUM(J5:J7) -> 805000 | K8: =IF(J8=0,0,(G8-J8)/J8) -> 32.493789 | L8: =IF(G8-I8<=0,"n/a",H8/(G8-I8)*12) -> 0.3127618 | M8: =IF(ISNUMBER(L8),L8*30.4375,"n/a") -> 9.5196872 | N8: =SUM(N5:N7) -> 1015000 | O8: =SUM(O5:O7) -> 80887500 | P8: =IF(N8=0,0,(O8-N8)/N8) -> 78.692118 | Q8: =SUM(Q5:Q7) -> 26857500
A10: Portfolio summary
A11: Total annual exposure before controls ($) | B11: ='Risk Calc'!E8 -> 35000000
A12: Annual risk reduction from all controls ($) | B12: =G8 -> 26962500
A13: Residual annual exposure after controls ($) | B13: =B11-B12 -> 8037500
A14: Exposure reduction (%) | B14: =IF(B11=0,0,B12/B11) -> 0.77035714
A15: Year-1 investment ($) | B15: =J8 -> 805000
A16: Year-1 portfolio ROI | B16: =K8 -> 32.493789

Sheet Charts
A1: Charts - Tasks 3 and 5
A2: All charts update from the Inputs tab.

Sheet Dashboard
A1: SecureBank Financial - SecureMobile Platform: Executive Risk Dashboard
A2: Prepared for the CISO and CFO | Lab 3b quantitative risk analysis | All figures in USD per year unless stated
A4: Total annual exposure | C4: Residual exposure after controls | E4: Annual risk reduction | G4: Year-1 investment | I4: Portfolio Year-1 ROI
A5: ='Risk Calc'!E8 -> 35000000 | C5: ='Control Analysis'!B13 -> 8037500 | E5: ='Control Analysis'!G8 -> 26962500 | G5: ='Control Analysis'!J8 -> 805000 | I5: ='Control Analysis'!K8 -> 32.493789
A7: Top 3 risks by financial impact
A8: Rank | B8: Vulnerability | C8: SLE ($) | D8: ARO | E8: ALE ($) | F8: Priority | G8: Heat rating
A9: 1 | B9: =INDEX('Risk Calc'!$B$5:$B$7,MATCH($A9,'Risk Calc'!$G$5:$G$7,0)) -> Database Injection | C9: =INDEX('Risk Calc'!$C$5:$C$7,MATCH($A9,'Risk Calc'!$G$5:$G$7,0)) -> 125000000 | D9: =INDEX('Risk Calc'!$D$5:$D$7,MATCH($A9,'Risk Calc'!$G$5:$G$7,0)) -> 0.25 | E9: =INDEX('Risk Calc'!$E$5:$E$7,MATCH($A9,'Risk Calc'!$G$5:$G$7,0)) -> 31250000 | F9: =INDEX('Risk Calc'!$H$5:$H$7,MATCH($A9,'Risk Calc'!$G$5:$G$7,0)) -> Critical | G9: =INDEX('Risk Calc'!$K$5:$K$7,MATCH($A9,'Risk Calc'!$G$5:$G$7,0)) -> High
A10: 2 | B10: =INDEX('Risk Calc'!$B$5:$B$7,MATCH($A10,'Risk Calc'!$G$5:$G$7,0)) -> Session Hijacking | C10: =INDEX('Risk Calc'!$C$5:$C$7,MATCH($A10,'Risk Calc'!$G$5:$G$7,0)) -> 7500000 | D10: =INDEX('Risk Calc'!$D$5:$D$7,MATCH($A10,'Risk Calc'!$G$5:$G$7,0)) -> 0.4 | E10: =INDEX('Risk Calc'!$E$5:$E$7,MATCH($A10,'Risk Calc'!$G$5:$G$7,0)) -> 3000000 | F10: =INDEX('Risk Calc'!$H$5:$H$7,MATCH($A10,'Risk Calc'!$G$5:$G$7,0)) -> High | G10: =INDEX('Risk Calc'!$K$5:$K$7,MATCH($A10,'Risk Calc'!$G$5:$G$7,0)) -> High
A11: 3 | B11: =INDEX('Risk Calc'!$B$5:$B$7,MATCH($A11,'Risk Calc'!$G$5:$G$7,0)) -> API Authentication Bypass | C11: =INDEX('Risk Calc'!$C$5:$C$7,MATCH($A11,'Risk Calc'!$G$5:$G$7,0)) -> 5000000 | D11: =INDEX('Risk Calc'!$D$5:$D$7,MATCH($A11,'Risk Calc'!$G$5:$G$7,0)) -> 0.15 | E11: =INDEX('Risk Calc'!$E$5:$E$7,MATCH($A11,'Risk Calc'!$G$5:$G$7,0)) -> 750000 | F11: =INDEX('Risk Calc'!$H$5:$H$7,MATCH($A11,'Risk Calc'!$G$5:$G$7,0)) -> Medium | G11: =INDEX('Risk Calc'!$K$5:$K$7,MATCH($A11,'Risk Calc'!$G$5:$G$7,0)) -> Medium
A13: Recommended controls
A14: # | B14: Control | C14: Initial cost ($) | D14: Annual maintenance ($) | E14: Year-1 cost ($) | F14: Annual risk reduction ($) | G14: Year-1 ROI | H14: Payback (months) | I14: Finding addressed | J14: Decision
A15: ='Control Analysis'!A5 -> 1 | B15: ='Control Analysis'!B5 -> Advanced API Security Gateway | C15: ='Control Analysis'!H5 -> 350000 | D15: ='Control Analysis'!I5 -> 50000 | E15: ='Control Analysis'!J5 -> 400000 | F15: ='Control Analysis'!G5 -> 675000 | G15: ='Control Analysis'!K5 -> 0.6875 | H15: ='Control Analysis'!L5 -> 6.72 | I15: ='Control Analysis'!D5 -> API Authentication Bypass | J15: ='Control Analysis'!R5 -> Recommend
A16: ='Control Analysis'!A6 -> 2 | B16: ='Control Analysis'!B6 -> Web Application Firewall (WAF) | C16: ='Control Analysis'!H6 -> 150000 | D16: ='Control Analysis'!I6 -> 25000 | E16: ='Control Analysis'!J6 -> 175000 | F16: ='Control Analysis'!G6 -> 23437500 | G16: ='Control Analysis'!K6 -> 132.92857 | H16: ='Control Analysis'!L6 -> 0.076882007 | I16: ='Control Analysis'!D6 -> Database Injection | J16: ='Control Analysis'!R6 -> Recommend
A17: ='Control Analysis'!A7 -> 3 | B17: ='Control Analysis'!B7 -> Multi-Factor Authentication Enhancement | C17: ='Control Analysis'!H7 -> 200000 | D17: ='Control Analysis'!I7 -> 30000 | E17: ='Control Analysis'!J7 -> 230000 | F17: ='Control Analysis'!G7 -> 2850000 | G17: ='Control Analysis'!K7 -> 11.391304 | H17: ='Control Analysis'!L7 -> 0.85106383 | I17: ='Control Analysis'!D7 -> Session Hijacking | J17: ='Control Analysis'!R7 -> Recommend
B18: Total | C18: ='Control Analysis'!H8 -> 700000 | D18: ='Control Analysis'!I8 -> 105000 | E18: ='Control Analysis'!J8 -> 805000 | F18: ='Control Analysis'!G8 -> 26962500 | G18: ='Control Analysis'!K8 -> 32.493789 | H18: ='Control Analysis'!L8 -> 0.3127618
F37: Key messages
F38: ="1. Top risk: "&B9&" ("&TEXT(E9,"$#,##0")&" ALE, "&TEXT(E9/'Risk Calc'!E8,"0%")&" of total exposure)." -> 1. Top risk: Database Injection ($31,250,000 ALE, 89% of total exposure).
F41: ="2. The recommended controls cost "&TEXT(E18,"$#,##0")&" in Year 1 and cut annual exposure by "&TEXT(F18,"$#,##0")&" ("&TEXT(F18/'Risk Calc'!E8,"0%")&")." -> 2. The recommended controls cost $805,000 in Year 1 and cut annual exposure by $26,962,500 (77%).
F44: ="3. Portfolio Year-1 ROI is "&TEXT(G18,"#,##0%")&" and the investment pays back in about "&TEXT(H18,"0.0")&" months." -> 3. Portfolio Year-1 ROI is 3,249% and the investment pays back in about 0.3 months.
F47: ="4. Residual exposure is still "&TEXT('Control Analysis'!B13,"$#,##0")&". Fix root causes in code and keep monitoring." -> 4. Residual exposure is still $8,037,500. Fix root causes in code and keep monitoring.

Sheet Gantt
A1: Task 7 - Risk treatment timeline (Gantt)
A2: Edit start day and duration (blue); bars update. Each column = one week. Day 0 = approval date.
F4: Week start day: | G4: =(G5-1)*7 -> 0 | H4: =(H5-1)*7 -> 7 | I4: =(I5-1)*7 -> 14 | J4: =(J5-1)*7 -> 21 | K4: =(K5-1)*7 -> 28 | L4: =(L5-1)*7 -> 35 | M4: =(M5-1)*7 -> 42 | N4: =(N5-1)*7 -> 49 | ... BF4: =(BF5-1)*7 -> 357
A5: Phase | B5: Task | C5: Addresses | D5: Start day | E5: Duration (days) | F5: End day | G5: 1 | H5: 2 | I5: 3 | J5: 4 | K5: 5 | L5: 6 | M5: 7 | N5: 8 | O5: 9 | P5: 10 | Q5: 11 | R5: 12 | S5: 13 | T5: 14 | U5: 15 | V5: 16 | W5: 17 | X5: 18 | Y5: 19 | Z5: 20 | AA5: 21 | AB5: 22 | AC5: 23 | AD5: 24 | AE5: 25 | AF5: 26 | AG5: 27 | AH5: 28 | AI5: 29 | AJ5: 30 | AK5: 31 | AL5: 32 | AM5: 33 | AN5: 34 | AO5: 35 | AP5: 36 | AQ5: 37 | AR5: 38 | AS5: 39 | AT5: 40 | AU5: 41 | AV5: 42 | AW5: 43 | AX5: 44 | AY5: 45 | AZ5: 46 | BA5: 47 | BB5: 48 | BC5: 49 | BD5: 50 | BE5: 51 | BF5: 52
A6: Immediate (0-30 days) | B6: Emergency virtual patching and WAF rules for injection flaw | C6: Finding 2 | D6: 0 | E6: 14 | F6: =D6+E6 -> 14
A7: Immediate (0-30 days) | B7: Deploy Web Application Firewall (WAF) | C7: Finding 2 | D7: 0 | E7: 30 | F7: =D7+E7 -> 30
A8: Immediate (0-30 days) | B8: Fix SQL injection in code (parameterized queries, input validation) | C8: Finding 2 | D8: 0 | E8: 30 | F8: =D8+E8 -> 30
A9: Immediate (0-30 days) | B9: Interim API rate limiting, logging and alerting (cut 48-hour detection) | C9: Finding 1 | D9: 0 | E9: 21 | F9: =D9+E9 -> 21
A10: Short-term (31-90 days) | B10: Select vendor and design API Security Gateway | C10: Finding 1 | D10: 30 | E10: 60 | F10: =D10+E10 -> 90
A11: Short-term (31-90 days) | B11: Pilot and roll out MFA enhancement | C11: Finding 3 | D11: 30 | E11: 60 | F11: =D11+E11 -> 90
A12: Short-term (31-90 days) | B12: Targeted re-test of injection and session fixes | C12: Findings 2, 3 | D12: 60 | E12: 30 | F12: =D12+E12 -> 90
A13: Long-term (91-365 days) | B13: Implement and cut over API Security Gateway | C13: Finding 1 | D13: 90 | E13: 120 | F13: =D13+E13 -> 210
A14: Long-term (91-365 days) | B14: Continuous monitoring and quarterly vulnerability scanning | C14: All findings | D14: 90 | E14: 275 | F14: =D14+E14 -> 365
A15: Long-term (91-365 days) | B15: Full penetration re-test and residual risk review | C15: All findings | D15: 300 | E15: 45 | F15: =D15+E15 -> 345
A16: Long-term (91-365 days) | B16: Annual risk quantification refresh and board report | C16: All findings | D16: 335 | E16: 30 | F16: =D16+E16 -> 365
A18: Legend: | B18: Immediate (0-30 days)
B19: Short-term (31-90 days)
B20: Long-term (91-365 days)

Sheet Bonus
A1: Bonus - Optimal control selection and combined risk-control matrix
A2: Tests all 8 combinations of controls against the Year-1 budget on Inputs (B33).
A3: Year-1 budget ($) | B3: =Inputs!B33 -> 500000
A5: Option analysis (1 = control selected)
A6: Option | B6: ='Control Analysis'!B5 -> Advanced API Security Gateway | C6: ='Control Analysis'!B6 -> Web Application Firewall (WAF) | D6: ='Control Analysis'!B7 -> Multi-Factor Authentication Enhancement | E6: Year-1 cost ($) | F6: Annual risk reduction ($) | G6: Net Year-1 benefit ($) | H6: Within budget? | I6: Eligible net benefit ($) | J6: Residual exposure ($)
A7: No controls | B7: 0 | C7: 0 | D7: 0 | E7: =B7*'Control Analysis'!$J$5+C7*'Control Analysis'!$J$6+D7*'Control Analysis'!$J$7 -> 0 | F7: =B7*'Control Analysis'!$G$5+C7*'Control Analysis'!$G$6+D7*'Control Analysis'!$G$7 -> 0 | G7: =F7-E7 -> 0 | H7: =IF(E7<=$B$3,"Yes","No") -> Yes | I7: =IF(H7="Yes",G7,"") -> 0 | J7: ='Risk Calc'!$E$8-F7 -> 35000000
A8: API Gateway only | B8: 1 | C8: 0 | D8: 0 | E8: =B8*'Control Analysis'!$J$5+C8*'Control Analysis'!$J$6+D8*'Control Analysis'!$J$7 -> 400000 | F8: =B8*'Control Analysis'!$G$5+C8*'Control Analysis'!$G$6+D8*'Control Analysis'!$G$7 -> 675000 | G8: =F8-E8 -> 275000 | H8: =IF(E8<=$B$3,"Yes","No") -> Yes | I8: =IF(H8="Yes",G8,"") -> 275000 | J8: ='Risk Calc'!$E$8-F8 -> 34325000
A9: WAF only | B9: 0 | C9: 1 | D9: 0 | E9: =B9*'Control Analysis'!$J$5+C9*'Control Analysis'!$J$6+D9*'Control Analysis'!$J$7 -> 175000 | F9: =B9*'Control Analysis'!$G$5+C9*'Control Analysis'!$G$6+D9*'Control Analysis'!$G$7 -> 23437500 | G9: =F9-E9 -> 23262500 | H9: =IF(E9<=$B$3,"Yes","No") -> Yes | I9: =IF(H9="Yes",G9,"") -> 23262500 | J9: ='Risk Calc'!$E$8-F9 -> 11562500
A10: MFA only | B10: 0 | C10: 0 | D10: 1 | E10: =B10*'Control Analysis'!$J$5+C10*'Control Analysis'!$J$6+D10*'Control Analysis'!$J$7 -> 230000 | F10: =B10*'Control Analysis'!$G$5+C10*'Control Analysis'!$G$6+D10*'Control Analysis'!$G$7 -> 2850000 | G10: =F10-E10 -> 2620000 | H10: =IF(E10<=$B$3,"Yes","No") -> Yes | I10: =IF(H10="Yes",G10,"") -> 2620000 | J10: ='Risk Calc'!$E$8-F10 -> 32150000
A11: API Gateway + WAF | B11: 1 | C11: 1 | D11: 0 | E11: =B11*'Control Analysis'!$J$5+C11*'Control Analysis'!$J$6+D11*'Control Analysis'!$J$7 -> 575000 | F11: =B11*'Control Analysis'!$G$5+C11*'Control Analysis'!$G$6+D11*'Control Analysis'!$G$7 -> 24112500 | G11: =F11-E11 -> 23537500 | H11: =IF(E11<=$B$3,"Yes","No") -> No | I11: =IF(H11="Yes",G11,"") | J11: ='Risk Calc'!$E$8-F11 -> 10887500
A12: API Gateway + MFA | B12: 1 | C12: 0 | D12: 1 | E12: =B12*'Control Analysis'!$J$5+C12*'Control Analysis'!$J$6+D12*'Control Analysis'!$J$7 -> 630000 | F12: =B12*'Control Analysis'!$G$5+C12*'Control Analysis'!$G$6+D12*'Control Analysis'!$G$7 -> 3525000 | G12: =F12-E12 -> 2895000 | H12: =IF(E12<=$B$3,"Yes","No") -> No | I12: =IF(H12="Yes",G12,"") | J12: ='Risk Calc'!$E$8-F12 -> 31475000
A13: WAF + MFA | B13: 0 | C13: 1 | D13: 1 | E13: =B13*'Control Analysis'!$J$5+C13*'Control Analysis'!$J$6+D13*'Control Analysis'!$J$7 -> 405000 | F13: =B13*'Control Analysis'!$G$5+C13*'Control Analysis'!$G$6+D13*'Control Analysis'!$G$7 -> 26287500 | G13: =F13-E13 -> 25882500 | H13: =IF(E13<=$B$3,"Yes","No") -> Yes | I13: =IF(H13="Yes",G13,"") -> 25882500 | J13: ='Risk Calc'!$E$8-F13 -> 8712500
A14: All three | B14: 1 | C14: 1 | D14: 1 | E14: =B14*'Control Analysis'!$J$5+C14*'Control Analysis'!$J$6+D14*'Control Analysis'!$J$7 -> 805000 | F14: =B14*'Control Analysis'!$G$5+C14*'Control Analysis'!$G$6+D14*'Control Analysis'!$G$7 -> 26962500 | G14: =F14-E14 -> 26157500 | H14: =IF(E14<=$B$3,"Yes","No") -> No | I14: =IF(H14="Yes",G14,"") | J14: ='Risk Calc'!$E$8-F14 -> 8037500
A16: Optimal option under budget | B16: =INDEX(A7:A14,MATCH(MAX(I7:I14),I7:I14,0)) -> WAF + MFA
A17: Net Year-1 benefit ($) | B17: =MAX(I7:I14) -> 25882500
A18: Year-1 cost ($) | B18: =INDEX(E7:E14,MATCH(MAX(I7:I14),I7:I14,0)) -> 405000
A19: Residual exposure ($) | B19: =INDEX(J7:J14,MATCH(MAX(I7:I14),I7:I14,0)) -> 8712500
A22: Combined risk-control matrix
A23: Finding | B23: Control | C23: Current ALE ($) | D23: Control Year-1 cost ($) | E23: Annual risk reduction ($) | F23: Residual ALE ($) | G23: Net Year-1 benefit ($) | H23: Benefit / cost ratio | I23: Selected under budget?
A24: ='Control Analysis'!D5 -> API Authentication Bypass | B24: ='Control Analysis'!B5 -> Advanced API Security Gateway | C24: ='Control Analysis'!E5 -> 750000 | D24: ='Control Analysis'!J5 -> 400000 | E24: ='Control Analysis'!G5 -> 675000 | F24: =C24-E24 -> 75000 | G24: =E24-D24 -> 275000 | H24: =IF(D24=0,0,E24/D24) -> 1.6875 | I24: =IF(INDEX(B$7:B$14,MATCH(MAX($I$7:$I$14),$I$7:$I$14,0))=1,"Yes","No") -> No
A25: ='Control Analysis'!D6 -> Database Injection | B25: ='Control Analysis'!B6 -> Web Application Firewall (WAF) | C25: ='Control Analysis'!E6 -> 31250000 | D25: ='Control Analysis'!J6 -> 175000 | E25: ='Control Analysis'!G6 -> 23437500 | F25: =C25-E25 -> 7812500 | G25: =E25-D25 -> 23262500 | H25: =IF(D25=0,0,E25/D25) -> 133.92857 | I25: =IF(INDEX(C$7:C$14,MATCH(MAX($I$7:$I$14),$I$7:$I$14,0))=1,"Yes","No") -> Yes
A26: ='Control Analysis'!D7 -> Session Hijacking | B26: ='Control Analysis'!B7 -> Multi-Factor Authentication Enhancement | C26: ='Control Analysis'!E7 -> 3000000 | D26: ='Control Analysis'!J7 -> 230000 | E26: ='Control Analysis'!G7 -> 2850000 | F26: =C26-E26 -> 150000 | G26: =E26-D26 -> 2620000 | H26: =IF(D26=0,0,E26/D26) -> 12.391304 | I26: =IF(INDEX(D$7:D$14,MATCH(MAX($I$7:$I$14),$I$7:$I$14,0))=1,"Yes","No") -> Yes
A27: Total | C27: =SUM(C24:C26) -> 35000000 | D27: =SUM(D24:D26) -> 805000 | E27: =SUM(E24:E26) -> 26962500 | F27: =SUM(F24:F26) -> 8037500 | G27: =SUM(G24:G26) -> 26157500 | H27: =IF(D27=0,0,E27/D27) -> 33.493789
A29: Note: the budget is an assumption (not in the lab). Selection maximises net Year-1 benefit among combinations whose Year-1 cost fits the budget.

Sheet Chart Data
A1: Chart data (helper ranges - do not edit)
A2: All values link to the analysis tabs.
A3: Cumulative net benefit by year ($) = annual risk reduction x year - (initial + maintenance x year)
A4: Year | B4: ='Control Analysis'!B5 -> Advanced API Security Gateway | C4: ='Control Analysis'!B6 -> Web Application Firewall (WAF) | D4: ='Control Analysis'!B7 -> Multi-Factor Authentication Enhancement | E4: All three controls
A5: 0 | B5: ='Control Analysis'!$G$5*$A5-('Control Analysis'!$H$5+'Control Analysis'!$I$5*$A5) -> -350000 | C5: ='Control Analysis'!$G$6*$A5-('Control Analysis'!$H$6+'Control Analysis'!$I$6*$A5) -> -150000 | D5: ='Control Analysis'!$G$7*$A5-('Control Analysis'!$H$7+'Control Analysis'!$I$7*$A5) -> -200000 | E5: =SUM(B5:D5) -> -700000
A6: 1 | B6: ='Control Analysis'!$G$5*$A6-('Control Analysis'!$H$5+'Control Analysis'!$I$5*$A6) -> 275000 | C6: ='Control Analysis'!$G$6*$A6-('Control Analysis'!$H$6+'Control Analysis'!$I$6*$A6) -> 23262500 | D6: ='Control Analysis'!$G$7*$A6-('Control Analysis'!$H$7+'Control Analysis'!$I$7*$A6) -> 2620000 | E6: =SUM(B6:D6) -> 26157500
A7: 2 | B7: ='Control Analysis'!$G$5*$A7-('Control Analysis'!$H$5+'Control Analysis'!$I$5*$A7) -> 900000 | C7: ='Control Analysis'!$G$6*$A7-('Control Analysis'!$H$6+'Control Analysis'!$I$6*$A7) -> 46675000 | D7: ='Control Analysis'!$G$7*$A7-('Control Analysis'!$H$7+'Control Analysis'!$I$7*$A7) -> 5440000 | E7: =SUM(B7:D7) -> 53015000
A8: 3 | B8: ='Control Analysis'!$G$5*$A8-('Control Analysis'!$H$5+'Control Analysis'!$I$5*$A8) -> 1525000 | C8: ='Control Analysis'!$G$6*$A8-('Control Analysis'!$H$6+'Control Analysis'!$I$6*$A8) -> 70087500 | D8: ='Control Analysis'!$G$7*$A8-('Control Analysis'!$H$7+'Control Analysis'!$I$7*$A8) -> 8260000 | E8: =SUM(B8:D8) -> 79872500
A9: 4 | B9: ='Control Analysis'!$G$5*$A9-('Control Analysis'!$H$5+'Control Analysis'!$I$5*$A9) -> 2150000 | C9: ='Control Analysis'!$G$6*$A9-('Control Analysis'!$H$6+'Control Analysis'!$I$6*$A9) -> 93500000 | D9: ='Control Analysis'!$G$7*$A9-('Control Analysis'!$H$7+'Control Analysis'!$I$7*$A9) -> 11080000 | E9: =SUM(B9:D9) -> 106730000
A10: 5 | B10: ='Control Analysis'!$G$5*$A10-('Control Analysis'!$H$5+'Control Analysis'!$I$5*$A10) -> 2775000 | C10: ='Control Analysis'!$G$6*$A10-('Control Analysis'!$H$6+'Control Analysis'!$I$6*$A10) -> 116912500 | D10: ='Control Analysis'!$G$7*$A10-('Control Analysis'!$H$7+'Control Analysis'!$I$7*$A10) -> 13900000 | E10: =SUM(B10:D10) -> 133587500
A13: Exposure before vs after controls
A14: Finding | B14: Current ALE ($) | C14: Residual ALE ($)
A15: ='Risk Calc'!B5 -> API Authentication Bypass | B15: ='Risk Calc'!E5 -> 750000 | C15: ='Risk Calc'!L5 -> 75000
A16: ='Risk Calc'!B6 -> Database Injection | B16: ='Risk Calc'!E6 -> 31250000 | C16: ='Risk Calc'!L6 -> 7812500
A17: ='Risk Calc'!B7 -> Session Hijacking | B17: ='Risk Calc'!E7 -> 3000000 | C17: ='Risk Calc'!L7 -> 150000
A20: Control investment breakdown (Year 1)
A21: Control | B21: Initial investment ($) | C21: Annual maintenance ($)
A22: ='Control Analysis'!B5 -> Advanced API Security Gateway | B22: ='Control Analysis'!H5 -> 350000 | C22: ='Control Analysis'!I5 -> 50000
A23: ='Control Analysis'!B6 -> Web Application Firewall (WAF) | B23: ='Control Analysis'!H6 -> 150000 | C23: ='Control Analysis'!I6 -> 25000
A24: ='Control Analysis'!B7 -> Multi-Factor Authentication Enhancement | B24: ='Control Analysis'!H7 -> 200000 | C24: ='Control Analysis'!I7 -> 30000
A27: Year-1 ROI by control
A28: Control | B28: Year-1 ROI
A29: ='Control Analysis'!B5 -> Advanced API Security Gateway | B29: ='Control Analysis'!K5 -> 0.6875
A30: ='Control Analysis'!B6 -> Web Application Firewall (WAF) | B30: ='Control Analysis'!K6 -> 132.92857
A31: ='Control Analysis'!B7 -> Multi-Factor Authentication Enhancement | B31: ='Control Analysis'!K7 -> 11.391304
